astyle_py/__init__.py
astyle_py/__main__.py
astyle_py/args.py
astyle_py/astyle_wrapper.py
astyle_py/files_iter.py
astyle_py/utils.py
astyle_py/version.py
astyle_py/lib/3.1/libastyle.wasm
astyle_py/lib/3.4.7/libastyle.wasm
astyle_py-1.1.0.dist-info/LICENSE
astyle_py-1.1.0.dist-info/METADATA
astyle_py-1.1.0.dist-info/WHEEL
astyle_py-1.1.0.dist-info/entry_points.txt
astyle_py-1.1.0.dist-info/top_level.txt
astyle_py-1.1.0.dist-info/RECORD
