Metadata-Version: 2.2
Name: astyle_py
Version: 1.1.0
Summary: Astyle, wrapped in a python package.
Author-email: Ivan Grokhotkov <ivan@espressif.com>
License: ### MIT License
Project-URL: Homepage, https://github.com/igrr/astyle_py
Classifier: Development Status :: 4 - Beta
Classifier: Environment :: Console
Classifier: Intended Audience :: Developers
Classifier: License :: OSI Approved :: MIT License
Classifier: Programming Language :: Python :: 3 :: Only
Requires-Python: >=3.9
License-File: LICENSE
Requires-Dist: wasmtime~=30.0.0
Requires-Dist: PyYAML~=6.0.1
Provides-Extra: dev
Requires-Dist: pytest; extra == "dev"
Requires-Dist: types-PyYAML; extra == "dev"
Requires-Dist: pre-commit; extra == "dev"
Requires-Dist: coverage; extra == "dev"
Requires-Dist: commitizen; extra == "dev"
